[
    {
        "text": "",
        "files": [
            {
                "id": "F08LEUQ917B",
                "created": 1743452072,
                "timestamp": 1743452072,
                "name": "IMG_6853.jpg",
                "title": "IMG_6853",
                "mimetype": "image\/jpeg",
                "filetype": "jpg",
                "pretty_type": "JPEG",
                "user": "U02NU6YUNBE",
                "user_team": "T02FQFVUX",
                "editable": false,
                "size": 2597240,
                "mode": "hosted",
                "is_external": false,
                "external_type": "",
                "is_public": true,
                "public_url_shared": false,
                "display_as_bot": false,
                "username": "",
                "url_private": "https:\/\/files.slack.com\/files-pri\/T02FQFVUX-F08LEUQ917B\/img_6853.jpg?t=xoxe-2534539983-8885985202723-8904052734993-1f37e7f31d32bd1a37398c0d5fdc9593",
                "url_private_download": "https:\/\/files.slack.com\/files-pri\/T02FQFVUX-F08LEUQ917B\/download\/img_6853.jpg?t=xoxe-2534539983-8885985202723-8904052734993-1f37e7f31d32bd1a37398c0d5fdc9593",
                "media_display_type": "unknown",
                "thumb_64": "https:\/\/files.slack.com\/files-tmb\/T02FQFVUX-F08LEUQ917B-45796415b0\/img_6853_64.jpg?t=xoxe-2534539983-8885985202723-8904052734993-1f37e7f31d32bd1a37398c0d5fdc9593",
                "thumb_80": "https:\/\/files.slack.com\/files-tmb\/T02FQFVUX-F08LEUQ917B-45796415b0\/img_6853_80.jpg?t=xoxe-2534539983-8885985202723-8904052734993-1f37e7f31d32bd1a37398c0d5fdc9593",
                "thumb_360": "https:\/\/files.slack.com\/files-tmb\/T02FQFVUX-F08LEUQ917B-45796415b0\/img_6853_360.jpg?t=xoxe-2534539983-8885985202723-8904052734993-1f37e7f31d32bd1a37398c0d5fdc9593",
                "thumb_360_w": 270,
                "thumb_360_h": 360,
                "thumb_480": "https:\/\/files.slack.com\/files-tmb\/T02FQFVUX-F08LEUQ917B-45796415b0\/img_6853_480.jpg?t=xoxe-2534539983-8885985202723-8904052734993-1f37e7f31d32bd1a37398c0d5fdc9593",
                "thumb_480_w": 360,
                "thumb_480_h": 480,
                "thumb_160": "https:\/\/files.slack.com\/files-tmb\/T02FQFVUX-F08LEUQ917B-45796415b0\/img_6853_160.jpg?t=xoxe-2534539983-8885985202723-8904052734993-1f37e7f31d32bd1a37398c0d5fdc9593",
                "thumb_720": "https:\/\/files.slack.com\/files-tmb\/T02FQFVUX-F08LEUQ917B-45796415b0\/img_6853_720.jpg?t=xoxe-2534539983-8885985202723-8904052734993-1f37e7f31d32bd1a37398c0d5fdc9593",
                "thumb_720_w": 540,
                "thumb_720_h": 720,
                "thumb_800": "https:\/\/files.slack.com\/files-tmb\/T02FQFVUX-F08LEUQ917B-45796415b0\/img_6853_800.jpg?t=xoxe-2534539983-8885985202723-8904052734993-1f37e7f31d32bd1a37398c0d5fdc9593",
                "thumb_800_w": 800,
                "thumb_800_h": 1067,
                "thumb_960": "https:\/\/files.slack.com\/files-tmb\/T02FQFVUX-F08LEUQ917B-45796415b0\/img_6853_960.jpg?t=xoxe-2534539983-8885985202723-8904052734993-1f37e7f31d32bd1a37398c0d5fdc9593",
                "thumb_960_w": 720,
                "thumb_960_h": 960,
                "thumb_1024": "https:\/\/files.slack.com\/files-tmb\/T02FQFVUX-F08LEUQ917B-45796415b0\/img_6853_1024.jpg?t=xoxe-2534539983-8885985202723-8904052734993-1f37e7f31d32bd1a37398c0d5fdc9593",
                "thumb_1024_w": 768,
                "thumb_1024_h": 1024,
                "original_w": 4284,
                "original_h": 5712,
                "thumb_tiny": "AwAwACR0jBZOe9SqoIBqJlDt9BTjIE+UZyO2aV7Ba4xp4g5UsVwccipSoI3A8EcVVxbSgsQwP1qyJFk+VMnHtRzByiq5UYAB+tL5x\/uioXkVDgnmm+fH60XYWRPgYx3PNVn3pKxiBxxwKsGRI1y7AE0IyOflOaW5WxRDFjt8tc+mMYqTlUOxlHqBUlwXZVMak+tV2D90b8qLJhdokaMyHdvWk8g\/30pUjkZQV24+tO8qb\/Y\/OnoKzIpwwmbd3PH0qS2GXz6Corrd5mcEgjipIVZYyxBGRgUX0DqSxNlFI9SKccn+tV0fZF+NTptkXJPNZmhWYshwM4pN7e9WiqUmEoA\/\/9k=",
                "permalink": "https:\/\/dali-lab.slack.com\/files\/U02FQFVUZ\/F08LEUQ917B\/img_6853.jpg",
                "permalink_public": "https:\/\/slack-files.com\/T02FQFVUX-F08LEUQ917B-14147c175d",
                "is_starred": false,
                "skipped_shares": true,
                "has_rich_preview": false,
                "file_access": "visible"
            }
        ],
        "upload": false,
        "user": "U02NU6YUNBE",
        "display_as_bot": false,
        "type": "message",
        "ts": "1743452082.686759",
        "client_msg_id": "EA538583-B01D-4F5D-BA43-B83175429D79",
        "thread_ts": "1743452082.686759",
        "reply_count": 4,
        "reply_users_count": 3,
        "latest_reply": "1743457647.082659",
        "reply_users": [
            "U065L7XPWMU",
            "U02NU6YUNBE",
            "U065SKAFVGB"
        ],
        "replies": [
            {
                "user": "U065L7XPWMU",
                "ts": "1743454386.768609"
            },
            {
                "user": "U02NU6YUNBE",
                "ts": "1743455057.223479"
            },
            {
                "user": "U065SKAFVGB",
                "ts": "1743457127.451119"
            },
            {
                "user": "U065L7XPWMU",
                "ts": "1743457647.082659"
            }
        ],
        "is_locked": false,
        "subscribed": false,
        "reactions": [
            {
                "name": "joker",
                "users": [
                    "U065L7XPWMU"
                ],
                "count": 1
            },
            {
                "name": "sair-escapism",
                "users": [
                    "U065L7XPWMU"
                ],
                "count": 1
            }
        ]
    },
    {
        "subtype": "channel_join",
        "user": "U065L7XPWMU",
        "text": "<@U065L7XPWMU> has joined the channel",
        "inviter": "U02NU6YUNBE",
        "type": "message",
        "ts": "1743452767.108389"
    },
    {
        "subtype": "channel_leave",
        "user": "UEEEXTKPC",
        "text": "<@UEEEXTKPC> has left the channel",
        "type": "message",
        "ts": "1743452794.251479"
    },
    {
        "subtype": "channel_leave",
        "user": "UERPQ8GLR",
        "text": "<@UERPQ8GLR> has left the channel",
        "type": "message",
        "ts": "1743452797.046529"
    },
    {
        "subtype": "channel_leave",
        "user": "U2AU4CRJB",
        "text": "<@U2AU4CRJB> has left the channel",
        "type": "message",
        "ts": "1743452799.184889"
    },
    {
        "subtype": "channel_leave",
        "user": "U04CD43C7K2",
        "text": "<@U04CD43C7K2> has left the channel",
        "type": "message",
        "ts": "1743452801.282879"
    },
    {
        "subtype": "channel_leave",
        "user": "U2BCMATG8",
        "text": "<@U2BCMATG8> has left the channel",
        "type": "message",
        "ts": "1743452803.714909"
    },
    {
        "subtype": "channel_leave",
        "user": "U4HQKF2CE",
        "text": "<@U4HQKF2CE> has left the channel",
        "type": "message",
        "ts": "1743452805.886719"
    },
    {
        "subtype": "channel_leave",
        "user": "UR3R195B3",
        "text": "<@UR3R195B3> has left the channel",
        "type": "message",
        "ts": "1743452808.172179"
    },
    {
        "subtype": "channel_leave",
        "user": "U3K5E37LJ",
        "text": "<@U3K5E37LJ> has left the channel",
        "type": "message",
        "ts": "1743452810.465739"
    },
    {
        "subtype": "channel_leave",
        "user": "U2ASM33DJ",
        "text": "<@U2ASM33DJ> has left the channel",
        "type": "message",
        "ts": "1743452812.531309"
    },
    {
        "subtype": "channel_leave",
        "user": "U024UN3KZNF",
        "text": "<@U024UN3KZNF> has left the channel",
        "type": "message",
        "ts": "1743452814.732449"
    },
    {
        "subtype": "channel_leave",
        "user": "U02P59WMP33",
        "text": "<@U02P59WMP33> has left the channel",
        "type": "message",
        "ts": "1743452817.119989"
    },
    {
        "subtype": "channel_leave",
        "user": "U2ASLLUJ3",
        "text": "<@U2ASLLUJ3> has left the channel",
        "type": "message",
        "ts": "1743452822.918239"
    },
    {
        "subtype": "channel_leave",
        "user": "UR2CH8AB1",
        "text": "<@UR2CH8AB1> has left the channel",
        "type": "message",
        "ts": "1743452825.400229"
    },
    {
        "subtype": "channel_leave",
        "user": "U01RZ3ZEM9T",
        "text": "<@U01RZ3ZEM9T> has left the channel",
        "type": "message",
        "ts": "1743452828.279609"
    },
    {
        "subtype": "channel_leave",
        "user": "UB1B3E6J3",
        "text": "<@UB1B3E6J3> has left the channel",
        "type": "message",
        "ts": "1743452830.610169"
    },
    {
        "subtype": "channel_leave",
        "user": "U0265GQ978B",
        "text": "<@U0265GQ978B> has left the channel",
        "type": "message",
        "ts": "1743452832.993019"
    },
    {
        "subtype": "channel_leave",
        "user": "UEERACZPF",
        "text": "<@UEERACZPF> has left the channel",
        "type": "message",
        "ts": "1743452835.978379"
    },
    {
        "subtype": "channel_leave",
        "user": "UQJ2WSJ4B",
        "text": "<@UQJ2WSJ4B> has left the channel",
        "type": "message",
        "ts": "1743452839.105169"
    },
    {
        "subtype": "channel_leave",
        "user": "U02M9TABR3R",
        "text": "<@U02M9TABR3R> has left the channel",
        "type": "message",
        "ts": "1743452841.219849"
    },
    {
        "subtype": "channel_leave",
        "user": "UGNU06USX",
        "text": "<@UGNU06USX> has left the channel",
        "type": "message",
        "ts": "1743452844.440839"
    },
    {
        "subtype": "channel_leave",
        "user": "U86Q8J7PS",
        "text": "<@U86Q8J7PS> has left the channel",
        "type": "message",
        "ts": "1743452846.485039"
    },
    {
        "subtype": "channel_leave",
        "user": "U03796DAGN8",
        "text": "<@U03796DAGN8> has left the channel",
        "type": "message",
        "ts": "1743452848.652169"
    },
    {
        "subtype": "channel_leave",
        "user": "U3K3N3LLR",
        "text": "<@U3K3N3LLR> has left the channel",
        "type": "message",
        "ts": "1743452850.800569"
    },
    {
        "subtype": "channel_leave",
        "user": "UEFC62739",
        "text": "<@UEFC62739> has left the channel",
        "type": "message",
        "ts": "1743452854.215439"
    },
    {
        "subtype": "channel_leave",
        "user": "U4P2HLX7U",
        "text": "<@U4P2HLX7U> has left the channel",
        "type": "message",
        "ts": "1743452856.278619"
    },
    {
        "subtype": "channel_leave",
        "user": "U2QA6LY9L",
        "text": "<@U2QA6LY9L> has left the channel",
        "type": "message",
        "ts": "1743452858.631469"
    },
    {
        "subtype": "channel_leave",
        "user": "UE32ESGK1",
        "text": "<@UE32ESGK1> has left the channel",
        "type": "message",
        "ts": "1743452860.720159"
    },
    {
        "subtype": "channel_leave",
        "user": "U01FF3UBT5J",
        "text": "<@U01FF3UBT5J> has left the channel",
        "type": "message",
        "ts": "1743452862.803429"
    },
    {
        "subtype": "channel_leave",
        "user": "U04BASJSJR1",
        "text": "<@U04BASJSJR1> has left the channel",
        "type": "message",
        "ts": "1743452864.770639"
    },
    {
        "subtype": "channel_leave",
        "user": "UEDK3SDJL",
        "text": "<@UEDK3SDJL> has left the channel",
        "type": "message",
        "ts": "1743452867.403459"
    },
    {
        "subtype": "channel_leave",
        "user": "U02QX2TF206",
        "text": "<@U02QX2TF206> has left the channel",
        "type": "message",
        "ts": "1743452870.204009"
    },
    {
        "subtype": "channel_leave",
        "user": "U03S8VDR2F8",
        "text": "<@U03S8VDR2F8> has left the channel",
        "type": "message",
        "ts": "1743452872.466269"
    },
    {
        "subtype": "channel_leave",
        "user": "U0HV4A35H",
        "text": "<@U0HV4A35H> has left the channel",
        "type": "message",
        "ts": "1743452875.014289"
    },
    {
        "subtype": "channel_leave",
        "user": "UGPUCBC59",
        "text": "<@UGPUCBC59> has left the channel",
        "type": "message",
        "ts": "1743452877.152189"
    },
    {
        "subtype": "channel_leave",
        "user": "U04UBTXHZ4L",
        "text": "<@U04UBTXHZ4L> has left the channel",
        "type": "message",
        "ts": "1743452879.171139",
        "reactions": [
            {
                "name": "meow-wtf",
                "users": [
                    "U03M4CR829G"
                ],
                "count": 1
            }
        ]
    },
    {
        "subtype": "channel_leave",
        "user": "UQT9H1B8Q",
        "text": "<@UQT9H1B8Q> has left the channel",
        "type": "message",
        "ts": "1743452881.120179"
    },
    {
        "subtype": "channel_leave",
        "user": "U2BT0FHAN",
        "text": "<@U2BT0FHAN> has left the channel",
        "type": "message",
        "ts": "1743452883.822329"
    },
    {
        "subtype": "channel_leave",
        "user": "U02L7KCKV",
        "text": "<@U02L7KCKV> has left the channel",
        "type": "message",
        "ts": "1743452886.004169"
    },
    {
        "subtype": "channel_leave",
        "user": "U02E9SQQ82W",
        "text": "<@U02E9SQQ82W> has left the channel",
        "type": "message",
        "ts": "1743452888.158499"
    },
    {
        "subtype": "channel_leave",
        "user": "U01623W4DLY",
        "text": "<@U01623W4DLY> has left the channel",
        "type": "message",
        "ts": "1743452890.534499"
    },
    {
        "subtype": "channel_leave",
        "user": "U0156G0Q1JA",
        "text": "<@U0156G0Q1JA> has left the channel",
        "type": "message",
        "ts": "1743452893.245429"
    },
    {
        "subtype": "channel_leave",
        "user": "U2AV42ZDL",
        "text": "<@U2AV42ZDL> has left the channel",
        "type": "message",
        "ts": "1743452895.418589"
    },
    {
        "subtype": "channel_leave",
        "user": "U01EUDG7DBP",
        "text": "<@U01EUDG7DBP> has left the channel",
        "type": "message",
        "ts": "1743452897.471659"
    },
    {
        "subtype": "channel_leave",
        "user": "U02P80NLNV9",
        "text": "<@U02P80NLNV9> has left the channel",
        "type": "message",
        "ts": "1743452899.796359"
    },
    {
        "subtype": "channel_leave",
        "user": "U02PB5LKVG9",
        "text": "<@U02PB5LKVG9> has left the channel",
        "type": "message",
        "ts": "1743452902.122219"
    },
    {
        "subtype": "channel_leave",
        "user": "U02NU573BM1",
        "text": "<@U02NU573BM1> has left the channel",
        "type": "message",
        "ts": "1743452904.466589"
    },
    {
        "subtype": "channel_leave",
        "user": "U02NH570249",
        "text": "<@U02NH570249> has left the channel",
        "type": "message",
        "ts": "1743452906.421179"
    },
    {
        "subtype": "channel_leave",
        "user": "U3J4LJRQD",
        "text": "<@U3J4LJRQD> has left the channel",
        "type": "message",
        "ts": "1743452909.337259"
    },
    {
        "subtype": "channel_leave",
        "user": "UE4JA8SS3",
        "text": "<@UE4JA8SS3> has left the channel",
        "type": "message",
        "ts": "1743452911.609999"
    },
    {
        "subtype": "channel_leave",
        "user": "U0B2UGXD4",
        "text": "<@U0B2UGXD4> has left the channel",
        "type": "message",
        "ts": "1743452913.514649"
    },
    {
        "subtype": "channel_leave",
        "user": "U0168KETM9R",
        "text": "<@U0168KETM9R> has left the channel",
        "type": "message",
        "ts": "1743452916.552189"
    },
    {
        "subtype": "channel_leave",
        "user": "U9USQS02Z",
        "text": "<@U9USQS02Z> has left the channel",
        "type": "message",
        "ts": "1743452918.879579"
    },
    {
        "subtype": "channel_leave",
        "user": "U04B8TZQZFH",
        "text": "<@U04B8TZQZFH> has left the channel",
        "type": "message",
        "ts": "1743452921.065409"
    },
    {
        "subtype": "channel_leave",
        "user": "U06EQRP7ALF",
        "text": "<@U06EQRP7ALF> has left the channel",
        "type": "message",
        "ts": "1743452923.115129"
    },
    {
        "subtype": "channel_leave",
        "user": "U5F6PS36D",
        "text": "<@U5F6PS36D> has left the channel",
        "type": "message",
        "ts": "1743452928.088319"
    },
    {
        "subtype": "channel_leave",
        "user": "U4S46GEB1",
        "text": "<@U4S46GEB1> has left the channel",
        "type": "message",
        "ts": "1743452930.580269"
    },
    {
        "subtype": "channel_leave",
        "user": "U0B7D5Y8G",
        "text": "<@U0B7D5Y8G> has left the channel",
        "type": "message",
        "ts": "1743452932.583999"
    },
    {
        "subtype": "channel_leave",
        "user": "U01R52WRHEW",
        "text": "<@U01R52WRHEW> has left the channel",
        "type": "message",
        "ts": "1743452934.966129"
    },
    {
        "subtype": "channel_leave",
        "user": "UETMAQ98F",
        "text": "<@UETMAQ98F> has left the channel",
        "type": "message",
        "ts": "1743452937.329259"
    },
    {
        "subtype": "channel_leave",
        "user": "U01S265HH1N",
        "text": "<@U01S265HH1N> has left the channel",
        "type": "message",
        "ts": "1743452939.175999"
    },
    {
        "subtype": "channel_leave",
        "user": "U015JPYEZEG",
        "text": "<@U015JPYEZEG> has left the channel",
        "type": "message",
        "ts": "1743452941.854769"
    },
    {
        "subtype": "channel_leave",
        "user": "U038N5GKGCE",
        "text": "<@U038N5GKGCE> has left the channel",
        "type": "message",
        "ts": "1743452944.042079"
    },
    {
        "subtype": "channel_leave",
        "user": "U02EBQSULMS",
        "text": "<@U02EBQSULMS> has left the channel",
        "type": "message",
        "ts": "1743452945.958509"
    },
    {
        "subtype": "channel_leave",
        "user": "U01EPL90H1U",
        "text": "<@U01EPL90H1U> has left the channel",
        "type": "message",
        "ts": "1743452947.698269"
    },
    {
        "subtype": "channel_leave",
        "user": "U0418V5N5MY",
        "text": "<@U0418V5N5MY> has left the channel",
        "type": "message",
        "ts": "1743452949.653439",
        "reactions": [
            {
                "name": "meow-wtf",
                "users": [
                    "U03M4CR829G"
                ],
                "count": 1
            }
        ]
    },
    {
        "subtype": "channel_leave",
        "user": "U3A66N0SE",
        "text": "<@U3A66N0SE> has left the channel",
        "type": "message",
        "ts": "1743452952.274379"
    },
    {
        "subtype": "channel_leave",
        "user": "U01R671S4BD",
        "text": "<@U01R671S4BD> has left the channel",
        "type": "message",
        "ts": "1743452954.366639"
    },
    {
        "subtype": "channel_leave",
        "user": "U015SJ0TTH9",
        "text": "<@U015SJ0TTH9> has left the channel",
        "type": "message",
        "ts": "1743452960.012249"
    },
    {
        "subtype": "channel_leave",
        "user": "UGREC91Q8",
        "text": "<@UGREC91Q8> has left the channel",
        "type": "message",
        "ts": "1743452963.539179"
    },
    {
        "subtype": "channel_leave",
        "user": "U6VHFFG1G",
        "text": "<@U6VHFFG1G> has left the channel",
        "type": "message",
        "ts": "1743452965.630339"
    },
    {
        "subtype": "channel_leave",
        "user": "UGNTJPS0L",
        "text": "<@UGNTJPS0L> has left the channel",
        "type": "message",
        "ts": "1743452967.440849"
    },
    {
        "subtype": "channel_leave",
        "user": "U01RUUL3RJL",
        "text": "<@U01RUUL3RJL> has left the channel",
        "type": "message",
        "ts": "1743452970.188839"
    },
    {
        "subtype": "channel_leave",
        "user": "U3JR72ADS",
        "text": "<@U3JR72ADS> has left the channel",
        "type": "message",
        "ts": "1743452972.909589"
    },
    {
        "subtype": "channel_leave",
        "user": "UQGTPRFPB",
        "text": "<@UQGTPRFPB> has left the channel",
        "type": "message",
        "ts": "1743452975.508729"
    },
    {
        "subtype": "channel_leave",
        "user": "UB03NGQG4",
        "text": "<@UB03NGQG4> has left the channel",
        "type": "message",
        "ts": "1743452977.728169"
    },
    {
        "subtype": "channel_leave",
        "user": "U0A07UGCB",
        "text": "<@U0A07UGCB> has left the channel",
        "type": "message",
        "ts": "1743452980.097969"
    },
    {
        "subtype": "channel_leave",
        "user": "U2C5UUPV2",
        "text": "<@U2C5UUPV2> has left the channel",
        "type": "message",
        "ts": "1743452982.669499"
    },
    {
        "subtype": "channel_leave",
        "user": "U4HPK7ELR",
        "text": "<@U4HPK7ELR> has left the channel",
        "type": "message",
        "ts": "1743452985.157419"
    },
    {
        "subtype": "channel_leave",
        "user": "UQT766K6U",
        "text": "<@UQT766K6U> has left the channel",
        "type": "message",
        "ts": "1743452987.350829"
    },
    {
        "subtype": "channel_leave",
        "user": "UCR1SE34M",
        "text": "<@UCR1SE34M> has left the channel",
        "type": "message",
        "ts": "1743452989.617719"
    },
    {
        "subtype": "channel_leave",
        "user": "U0VUVRQ82",
        "text": "<@U0VUVRQ82> has left the channel",
        "type": "message",
        "ts": "1743452992.985819"
    },
    {
        "subtype": "channel_leave",
        "user": "U01FBU7HX2S",
        "text": "<@U01FBU7HX2S> has left the channel",
        "type": "message",
        "ts": "1743452999.467049"
    },
    {
        "subtype": "channel_join",
        "user": "U0168KETM9R",
        "text": "<@U0168KETM9R> has joined the channel",
        "inviter": "U0377AVSG66",
        "type": "message",
        "ts": "1743453467.752609"
    },
    {
        "user": "U065L7XPWMU",
        "type": "message",
        "ts": "1743454386.768609",
        "client_msg_id": "9D061D7A-F21E-4152-B458-0ADC2271C97E",
        "text": "i didnt even notice u taking the picture :skull_and_crossbones: ",
        "team": "T02FQFVUX",
        "user_team": "T02FQFVUX",
        "source_team": "T02FQFVUX",
        "user_profile": {
            "avatar_hash": "18502dc99b29",
            "image_72": "https:\/\/avatars.slack-edge.com\/2025-02-21\/8494394124691_18502dc99b29f70d9d24_72.png",
            "first_name": "sophie",
            "real_name": "sophie park",
            "display_name": "sophie park",
            "team": "T02FQFVUX",
            "name": "sophie.park",
            "is_restricted": false,
            "is_ultra_restricted": false
        },
        "thread_ts": "1743452082.686759",
        "parent_user_id": "U02NU6YUNBE",
        "blocks": [
            {
                "type": "rich_text",
                "block_id": "CjDhA",
                "elements": [
                    {
                        "type": "rich_text_section",
                        "elements": [
                            {
                                "type": "text",
                                "text": "i didnt even notice u taking the picture "
                            },
                            {
                                "type": "emoji",
                                "name": "skull_and_crossbones",
                                "unicode": "2620-fe0f"
                            },
                            {
                                "type": "text",
                                "text": " "
                            }
                        ]
                    }
                ]
            }
        ]
    },
    {
        "user": "U02NU6YUNBE",
        "type": "message",
        "ts": "1743455057.223479",
        "client_msg_id": "97D78417-798E-4B39-87DF-9B1B9EB03E7D",
        "text": "yeah that’s kinda hard to do when ur asleep i agree :skull: ",
        "team": "T02FQFVUX",
        "user_team": "T02FQFVUX",
        "source_team": "T02FQFVUX",
        "user_profile": {
            "avatar_hash": "ea03327be9e7",
            "image_72": "https:\/\/avatars.slack-edge.com\/2021-11-27\/2774009006803_ea03327be9e748c7727f_72.jpg",
            "first_name": "Eric",
            "real_name": "Eric Lu",
            "display_name": "Eric Lu",
            "team": "T02FQFVUX",
            "name": "eric.lu",
            "is_restricted": false,
            "is_ultra_restricted": false
        },
        "thread_ts": "1743452082.686759",
        "parent_user_id": "U02NU6YUNBE",
        "blocks": [
            {
                "type": "rich_text",
                "block_id": "rVTtV",
                "elements": [
                    {
                        "type": "rich_text_section",
                        "elements": [
                            {
                                "type": "text",
                                "text": "yeah that’s kinda hard to do when ur asleep i agree "
                            },
                            {
                                "type": "emoji",
                                "name": "skull",
                                "unicode": "1f480"
                            },
                            {
                                "type": "text",
                                "text": " "
                            }
                        ]
                    }
                ]
            }
        ]
    },
    {
        "user": "U065SKAFVGB",
        "type": "message",
        "ts": "1743457127.451119",
        "client_msg_id": "03C0512B-96FA-407C-B798-41E50E782B8F",
        "text": "also kinda hard to do for sophie in general",
        "team": "T02FQFVUX",
        "user_team": "T02FQFVUX",
        "source_team": "T02FQFVUX",
        "user_profile": {
            "avatar_hash": "4235f5cf880b",
            "image_72": "https:\/\/avatars.slack-edge.com\/2024-05-09\/7089184506006_4235f5cf880b2820484e_72.jpg",
            "first_name": "Sair",
            "real_name": "Sair Shaikh",
            "display_name": "Sair Shaikh",
            "team": "T02FQFVUX",
            "name": "sair.shaikh",
            "is_restricted": false,
            "is_ultra_restricted": false
        },
        "thread_ts": "1743452082.686759",
        "parent_user_id": "U02NU6YUNBE",
        "blocks": [
            {
                "type": "rich_text",
                "block_id": "gy\/9e",
                "elements": [
                    {
                        "type": "rich_text_section",
                        "elements": [
                            {
                                "type": "text",
                                "text": "also kinda hard to do for sophie in general"
                            }
                        ]
                    }
                ]
            }
        ]
    },
    {
        "user": "U065L7XPWMU",
        "type": "message",
        "ts": "1743457647.082659",
        "client_msg_id": "C804D061-240D-45D6-BB5F-0265C78FD06C",
        "text": "what does that even mean :sob:  ",
        "team": "T02FQFVUX",
        "user_team": "T02FQFVUX",
        "source_team": "T02FQFVUX",
        "user_profile": {
            "avatar_hash": "18502dc99b29",
            "image_72": "https:\/\/avatars.slack-edge.com\/2025-02-21\/8494394124691_18502dc99b29f70d9d24_72.png",
            "first_name": "sophie",
            "real_name": "sophie park",
            "display_name": "sophie park",
            "team": "T02FQFVUX",
            "name": "sophie.park",
            "is_restricted": false,
            "is_ultra_restricted": false
        },
        "thread_ts": "1743452082.686759",
        "parent_user_id": "U02NU6YUNBE",
        "blocks": [
            {
                "type": "rich_text",
                "block_id": "HaJml",
                "elements": [
                    {
                        "type": "rich_text_section",
                        "elements": [
                            {
                                "type": "text",
                                "text": "what does that even mean "
                            },
                            {
                                "type": "emoji",
                                "name": "sob",
                                "unicode": "1f62d"
                            },
                            {
                                "type": "text",
                                "text": "  "
                            }
                        ]
                    }
                ]
            }
        ]
    },
    {
        "subtype": "channel_join",
        "user": "U06C578VAGL",
        "text": "<@U06C578VAGL> has joined the channel",
        "type": "message",
        "ts": "1743460146.963879"
    }
]